__init__.py
search_management.py
properly_models-0.0.3.dist-info/METADATA
properly_models-0.0.3.dist-info/WHEEL
properly_models-0.0.3.dist-info/top_level.txt
properly_models-0.0.3.dist-info/RECORD
