Metadata-Version: 2.1
Name: properly-models
Version: 0.0.3
Summary: Models for common Properly operations in python.
Home-page: https://github.com/GoProperly/properly-models
Author: GoProperly
Author-email: info@goproperly.com
License: UNKNOWN
Platform: UNKNOWN
Classifier: Programming Language :: Python :: 3.6
Classifier: Programming Language :: Python :: 3.7
Classifier: Programming Language :: Python :: 3.8
